logres/__init__.py
logres-0.0.1.dist-info/METADATA
logres-0.0.1.dist-info/WHEEL
logres-0.0.1.dist-info/entry_points.txt
logres-0.0.1.dist-info/RECORD
